Examples/face/face_test.py
Examples/hand/hand_change_background.py
Examples/hand/hand_change_style.py
Examples/hand/hand_debug.py
Examples/hand/hand_landmark_distance.py
Examples/pose/pose_test.py
Examples/selfie_segmentation/selfie_test.py
pumpkinpipe/__init__.py
pumpkinpipe/face.py
pumpkinpipe/hand.py
pumpkinpipe/pose.py
pumpkinpipe/selfie_segmentation.py
pumpkinpipe/models/__init__.py
pumpkinpipe/models/face_landmarker.task
pumpkinpipe/models/hand_landmarker.task
pumpkinpipe/models/pose_landmarker_full.task
pumpkinpipe/models/selfie_segmenter.tflite
pumpkinpipe/utils/drawing.py
pumpkinpipe/utils/model_loader.py
pumpkinpipe/utils/text.py
pumpkinpipe-0.1.0.dist-info/licenses/LICENSE
pumpkinpipe-0.1.0.dist-info/METADATA
pumpkinpipe-0.1.0.dist-info/WHEEL
pumpkinpipe-0.1.0.dist-info/top_level.txt
pumpkinpipe-0.1.0.dist-info/RECORD
