Metadata-Version: 2.4
Name: pumpkinpipe
Version: 0.1.0
Summary: Student-friendly MediaPipe Tasks wrapper
License: Copyright (c) 2026 SmugPumpkins
Requires-Python: >=3.10
License-File: LICENSE
Requires-Dist: mediapipe>=0.10
Requires-Dist: opencv-python
Requires-Dist: numpy
Dynamic: license-file
